{
  "project_info": {
    "project_number": "481823728180",
    "project_id": "fastconnectapp",
    "storage_bucket": "fastconnectapp.firebasestorage.app"
  },
  "client": [
    {
      "client_info": {
        "mobilesdk_app_id": "1:481823728180:android:8f096e64574dc7c4ce6061",
        "android_client_info": {
          "package_name": "com.example.fastconnect_app"
        }
      },
      "oauth_client": [],
      "api_key": [
        {
          "current_key": "AIzaSyB3N9HcEXptx_pIafcCvtxBxEn10OO2fkQ"
        }
      ],
      "services": {
        "appinvite_service": {
          "other_platform_oauth_client": []
        }
      }
    }
  ],
  "configuration_version": "1"
}